SQLamarr-0.0rc7.dist-info/METADATA
SQLamarr-0.0rc7.dist-info/WHEEL
SQLamarr-0.0rc7.dist-info/RECORD
SQLamarr-0.0rc7.dist-info/top_level.txt
SQLamarr-0.0rc7.dist-info/LICENSE
SQLamarr.libs/libsqlite3-68cb97d5.so.0.8.6
SQLamarr.libs/libHepMC3-d8372169.so.3
SQLamarr/EditEventStore.py
SQLamarr/MCParticleSelector.py
SQLamarr/_find_CDLL.py
SQLamarr/TemporaryTable.py
SQLamarr/__init__.py
SQLamarr/PVReconstruction.py
SQLamarr/PyTransformer.py
SQLamarr/HepMC2DataLoader.py
SQLamarr/CleanEventStore.py
SQLamarr/PVFinder.py
SQLamarr/Plugin.py
SQLamarr/UpdateDBConnection.py
SQLamarr/Pipeline.py
SQLamarr/GenerativePlugin.py
SQLamarr/db_functions.py
SQLamarr/libSQLamarr.cpython-39-x86_64-linux-gnu.so
