Metadata-Version: 2.1
Name: SQLamarr
Version: 0.0rc7
Summary: The stand-alone ultra-fast simulation option for LHCb
Author-email: Lucio Anderlini <Lucio.Anderlini@fi.infn.it>, Matteo Barbetti <Matteo.Barbetti@fi.infn.it>
License: GPL-3
Project-URL: Homepage, https://lamarrsim.github.io/SQLamarr/
Project-URL: Source, https://github.com/LamarrSim/SQLamarr
Keywords: lhcb,fast-simulation,simulation,hep,physics
Classifier: Development Status :: 3 - Alpha
Classifier: Programming Language :: Python :: 3
Classifier: Programming Language :: SQL
Classifier: Programming Language :: C++
Classifier: Operating System :: POSIX :: Linux
Classifier: Intended Audience :: Science/Research
Classifier: Topic :: Scientific/Engineering :: Physics
Classifier: License :: OSI Approved :: GNU General Public License v3 (GPLv3)
Classifier: Environment :: Console
License-File: LICENSE
Requires-Dist: hepmc3
